fastapi_agents/__init__.py
fastapi_agents/core.py
fastapi_agents/crewai.py
fastapi_agents/errors.py
fastapi_agents/llama_index.py
fastapi_agents/logs.py
fastapi_agents/models.py
fastapi_agents/pydantic_ai.py
fastapi_agents/smolagents.py
fastapi_agents-0.1.28.dist-info/METADATA
fastapi_agents-0.1.28.dist-info/WHEEL
fastapi_agents-0.1.28.dist-info/entry_points.txt
fastapi_agents-0.1.28.dist-info/licenses/LICENSE
fastapi_agents-0.1.28.dist-info/RECORD
