Metadata-Version: 2.3
Name: fastapi-agents
Version: 0.1.28
Summary: A FastAPI extension for integrating common AI agent frameworks.
Project-URL: Repository, https://github.com/blairhudson/fastapi-agents
Author-email: Blair Hudson <blairhudson@users.noreply.github.com>
License: MIT License
Keywords: agents,ai,fastapi,llama-index,pydantic-ai,smolagents
Classifier: Development Status :: 3 - Alpha
Classifier: Framework :: FastAPI
Classifier: License :: OSI Approved :: MIT License
Classifier: Operating System :: OS Independent
Classifier: Programming Language :: Python
Classifier: Programming Language :: Python :: 3
Classifier: Programming Language :: Python :: 3.12
Requires-Python: >=3.12
Requires-Dist: fastapi>=0.115.6
Provides-Extra: crewai
Requires-Dist: crewai>=0.95.0; extra == 'crewai'
Provides-Extra: llama-index
Requires-Dist: llama-index>=0.12.10; extra == 'llama-index'
Provides-Extra: pydantic-ai
Requires-Dist: pydantic-ai>=0.0.18; extra == 'pydantic-ai'
Provides-Extra: security
Requires-Dist: python-multipart>=0.0.20; extra == 'security'
Provides-Extra: smolagents
Requires-Dist: litellm>=1.57.8; extra == 'smolagents'
Requires-Dist: smolagents>=1.2.2; extra == 'smolagents'
Provides-Extra: uvicorn
Requires-Dist: uvicorn>=0.34.0; extra == 'uvicorn'
